solids/__init__.py
solids/calc.py
solids/cli.py
solids/heuristic.py
solids/libcrossover.py
solids/libdiscmbtrcrystals.py
solids/libmakextal.py
solids/libmutants.py
solids/libtools.py
solids-0.3.4.dist-info/licenses/LICENSE
solids-0.3.4.dist-info/METADATA
solids-0.3.4.dist-info/WHEEL
solids-0.3.4.dist-info/entry_points.txt
solids-0.3.4.dist-info/top_level.txt
solids-0.3.4.dist-info/RECORD
