Metadata-Version: 2.4
Name: solids
Version: 0.3.4
Summary: Solids: A tool for crystal structure prediction
Author-email: Carlos Lopez-Castro <filiberto.ortiz@cinvestav.mx>
License-Expression: MIT
Project-URL: Homepage, https://github.com/Carloast0790/SolidASE_0.0
Requires-Python: >=3.9
License-File: LICENSE
Requires-Dist: ase==3.23
Requires-Dist: aegon==1.2.1
Requires-Dist: pyxtal
Requires-Dist: dscribe
Dynamic: license-file
